./.gitignore
./.python-version
./CHANGELOG.md
./PKG-INFO
./README.md
./main.py
./pyproject.toml
./uv.lock
./.claude/settings.local.json
./tests/__init__.py
./tests/conftest.py
./tests/test_converter.py
./tests/fixtures/empty.csv
./tests/fixtures/english.csv
./tests/fixtures/english.yaml
./tests/fixtures/korean.csv
./tests/fixtures/korean.yaml
./tests/fixtures/mixed.csv
./tests/fixtures/mixed.yaml
./tests/fixtures/multiline.yaml
./tests/fixtures/single_object.yaml
./tests/fixtures/special_chars.csv
csv_to_yaml-0.1.1.dist-info/METADATA
csv_to_yaml-0.1.1.dist-info/WHEEL
csv_to_yaml-0.1.1.dist-info/entry_points.txt
csv_to_yaml-0.1.1.dist-info/RECORD
