Metadata-Version: 2.4
Name: csv-to-yaml
Version: 0.1.1
Summary: Lightweight CSV to YAML and YAML to CSV converter
Author: Dongook Son
License: MIT
Classifier: License :: OSI Approved :: MIT License
Classifier: Operating System :: OS Independent
Classifier: Programming Language :: Python :: 3
Requires-Python: >=3.13
Requires-Dist: pyyaml>=6.0
